[{"ts": 1751028149, "freq": 7.83, "amp": 1.74}, {"ts": 1751031093, "freq": 7.83, "amp": 1.29}, {"ts": 1751034009, "freq": 7.83, "amp": 2.54}, {"ts": 1751037730, "freq": 7.83, "amp": -1.28}, {"ts": 1751041624, "freq": 7.83, "amp": -0.83}, {"ts": 1751044708, "freq": 7.83, "amp": 1.47}, {"ts": 1751048978, "freq": 7.83, "amp": 3.09}, {"ts": 1751051731, "freq": 7.83, "amp": 0.38}, {"ts": 1751055774, "freq": 7.83, "amp": 0.78}, {"ts": 1751059050, "freq": 7.83, "amp": -2.09}, {"ts": 1751062882, "freq": 7.83, "amp": -0.24}, {"ts": 1751066419, "freq": 7.83, "amp": 1.51}, {"ts": 1751075041, "freq": 7.83, "amp": 2.11}, {"ts": 1751080468, "freq": 7.83, "amp": -0.56}, {"ts": 1751084741, "freq": 7.83, "amp": 0.83}, {"ts": 1751088039, "freq": 7.83, "amp": -1.53}, {"ts": 1751092102, "freq": 7.83, "amp": -1.45}, {"ts": 1751095129, "freq": 7.83, "amp": 0.41}, {"ts": 1751099130, "freq": 7.83, "amp": 2.51}, {"ts": 1751102528, "freq": 7.83, "amp": 0.1}, {"ts": 1751106018, "freq": 7.83, "amp": -2.87}, {"ts": 1751109391, "freq": 7.83, "amp": -1.64}, {"ts": 1751114350, "freq": 7.83, "amp": -0.51}, {"ts": 1751117292, "freq": 7.83, "amp": 0.57}, {"ts": 1751120265, "freq": 7.83, "amp": -0.71}, {"ts": 1751123987, "freq": 7.83, "amp": 1.84}, {"ts": 1751127851, "freq": 7.83, "amp": 0.4}, {"ts": 1751131039, "freq": 7.83, "amp": 3.3}, {"ts": 1751135232, "freq": 7.83, "amp": 0.89}, {"ts": 1751138145, "freq": 7.83, "amp": -0.34}, {"ts": 1751142076, "freq": 7.83, "amp": -0.34}, {"ts": 1751145503, "freq": 7.83, "amp": 2.49}, {"ts": 1751149125, "freq": 7.83, "amp": 0.09}, {"ts": 1751152761, "freq": 7.83, "amp": 0.12}, {"ts": 1751162226, "freq": 7.83, "amp": 0.7}, {"ts": 1751168324, "freq": 7.83, "amp": -1.14}, {"ts": 1751171816, "freq": 7.83, "amp": -0.39}, {"ts": 1751174587, "freq": 7.83, "amp": -1.86}, {"ts": 1751178592, "freq": 7.83, "amp": -1.61}, {"ts": 1751181568, "freq": 7.83, "amp": -3.49}, {"ts": 1751185578, "freq": 7.83, "amp": -2.41}, {"ts": 1751188807, "freq": 7.83, "amp": -2.75}, {"ts": 1751192603, "freq": 7.83, "amp": -2.52}, {"ts": 1751195778, "freq": 7.83, "amp": 2.64}, {"ts": 1751200789, "freq": 7.83, "amp": -0.97}, {"ts": 1751203727, "freq": 7.83, "amp": -3.06}, {"ts": 1751206663, "freq": 7.83, "amp": -3.06}, {"ts": 1751210396, "freq": 7.83, "amp": -1.66}, {"ts": 1751214271, "freq": 7.83, "amp": -4.66}, {"ts": 1751217432, "freq": 7.83, "amp": -4.18}, {"ts": 1751221650, "freq": 7.83, "amp": -1.13}, {"ts": 1751224559, "freq": 7.83, "amp": -1.56}, {"ts": 1751228509, "freq": 7.83, "amp": -0.85}, {"ts": 1751231924, "freq": 7.83, "amp": -1.32}, {"ts": 1751235554, "freq": 7.83, "amp": -3.61}, {"ts": 1751239164, "freq": 7.83, "amp": -1.16}, {"ts": 1751248366, "freq": 7.83, "amp": -1.3}, {"ts": 1751253932, "freq": 7.83, "amp": -0.16}, {"ts": 1751258072, "freq": 7.83, "amp": -4.33}, {"ts": 1751261015, "freq": 7.83, "amp": -0.18}, {"ts": 1751265177, "freq": 7.83, "amp": -3.14}, {"ts": 1751268142, "freq": 7.83, "amp": -2.99}, {"ts": 1751272185, "freq": 7.83, "amp": -4.28}, {"ts": 1751275525, "freq": 7.83, "amp": -4.76}, {"ts": 1751279018, "freq": 7.83, "amp": -1.77}, {"ts": 1751282297, "freq": 7.83, "amp": 2.94}, {"ts": 1751287430, "freq": 7.83, "amp": 2.33}, {"ts": 1751290434, "freq": 7.83, "amp": 2.11}, {"ts": 1751293257, "freq": 7.83, "amp": 1.23}, {"ts": 1751297035, "freq": 7.83, "amp": -3.27}, {"ts": 1751300827, "freq": 7.83, "amp": -5.63}, {"ts": 1751303929, "freq": 7.83, "amp": 3.28}, {"ts": 1751308212, "freq": 7.83, "amp": 2.4}, {"ts": 1751310983, "freq": 7.83, "amp": -0.28}, {"ts": 1751314964, "freq": 7.83, "amp": -3.13}, {"ts": 1751318368, "freq": 7.83, "amp": -3.17}, {"ts": 1751322027, "freq": 7.83, "amp": -3.74}, {"ts": 1751325584, "freq": 7.83, "amp": -3.45}, {"ts": 1751335095, "freq": 7.83, "amp": -1.97}, {"ts": 1751341351, "freq": 7.83, "amp": 0.17}, {"ts": 1751344730, "freq": 7.83, "amp": -0.94}, {"ts": 1751347450, "freq": 7.83, "amp": 0.31}, {"ts": 1751351560, "freq": 7.83, "amp": 3.31}, {"ts": 1751354554, "freq": 7.83, "amp": 2.29}, {"ts": 1751358572, "freq": 7.83, "amp": 0.85}, {"ts": 1751361915, "freq": 7.83, "amp": -0.7}, {"ts": 1751365439, "freq": 7.83, "amp": 1.94}, {"ts": 1751368706, "freq": 7.83, "amp": 1.22}, {"ts": 1751373837, "freq": 7.83, "amp": 4.09}, {"ts": 1751376836, "freq": 7.83, "amp": 4.7}, {"ts": 1751379621, "freq": 7.83, "amp": 5.11}, {"ts": 1751383371, "freq": 7.83, "amp": 4.94}, {"ts": 1751387238, "freq": 7.83, "amp": 4.94}, {"ts": 1751390326, "freq": 7.83, "amp": 1.42}, {"ts": 1751394605, "freq": 7.83, "amp": -0.13}, {"ts": 1751397390, "freq": 7.83, "amp": -0.59}, {"ts": 1751401410, "freq": 7.83, "amp": 0.51}, {"ts": 1751404779, "freq": 7.83, "amp": 1.17}, {"ts": 1751408398, "freq": 7.83, "amp": 1.17}, {"ts": 1751411990, "freq": 7.83, "amp": -0.91}, {"ts": 1751420849, "freq": 7.83, "amp": -1.67}, {"ts": 1751426364, "freq": 7.83, "amp": -2.12}, {"ts": 1751430641, "freq": 7.83, "amp": -1.15}, {"ts": 1751433823, "freq": 7.83, "amp": -2.61}, {"ts": 1751437926, "freq": 7.83, "amp": -1.66}, {"ts": 1751440865, "freq": 7.83, "amp": -1.52}, {"ts": 1751444956, "freq": 7.83, "amp": -2.28}, {"ts": 1751448303, "freq": 7.83, "amp": -2.83}, {"ts": 1751451801, "freq": 7.83, "amp": -2.19}, {"ts": 1751455105, "freq": 7.83, "amp": -3.01}, {"ts": 1751460205, "freq": 7.83, "amp": -1.5}, {"ts": 1751463195, "freq": 7.83, "amp": -1.69}, {"ts": 1751466041, "freq": 7.83, "amp": -0.53}, {"ts": 1751469811, "freq": 7.83, "amp": -2.74}, {"ts": 1751473611, "freq": 7.83, "amp": -3.87}, {"ts": 1751476748, "freq": 7.83, "amp": -3.69}, {"ts": 1751481019, "freq": 7.83, "amp": -1.6}, {"ts": 1751483818, "freq": 7.83, "amp": 0.08}, {"ts": 1751487705, "freq": 7.83, "amp": -1.4}, {"ts": 1751491188, "freq": 7.83, "amp": 0.38}, {"ts": 1751494779, "freq": 7.83, "amp": -2.53}, {"ts": 1751498477, "freq": 7.83, "amp": -3.46}, {"ts": 1751507261, "freq": 7.83, "amp": -2.1}, {"ts": 1751512840, "freq": 7.83, "amp": -5.85}, {"ts": 1751517163, "freq": 7.83, "amp": 3.1}, {"ts": 1751520264, "freq": 7.83, "amp": -6.35}, {"ts": 1751524347, "freq": 7.83, "amp": 9.44}, {"ts": 1751527253, "freq": 7.83, "amp": 8.15}, {"ts": 1751531316, "freq": 7.83, "amp": 12.09}, {"ts": 1751534600, "freq": 7.83, "amp": 12.9}, {"ts": 1751538215, "freq": 7.83, "amp": 9.61}, {"ts": 1751541512, "freq": 7.83, "amp": 10.02}, {"ts": 1751546523, "freq": 7.83, "amp": -1.39}, {"ts": 1751549556, "freq": 7.83, "amp": 6.96}, {"ts": 1751552426, "freq": 7.83, "amp": 5.35}, {"ts": 1751556177, "freq": 7.83, "amp": 5.77}, {"ts": 1751560012, "freq": 7.83, "amp": 3.78}, {"ts": 1751563241, "freq": 7.83, "amp": -0.62}, {"ts": 1751567396, "freq": 7.83, "amp": -6.66}, {"ts": 1751570190, "freq": 7.83, "amp": -6.5}, {"ts": 1751574178, "freq": 7.83, "amp": -6.67}, {"ts": 1751577555, "freq": 7.83, "amp": -6.67}, {"ts": 1751581173, "freq": 7.83, "amp": -7.96}, {"ts": 1751584800, "freq": 7.83, "amp": -4.45}, {"ts": 1751593655, "freq": 7.83, "amp": -5.58}, {"ts": 1751599129, "freq": 7.83, "amp": -5.75}, {"ts": 1751603462, "freq": 7.83, "amp": -4.32}, {"ts": 1751606628, "freq": 7.83, "amp": -3.5}, {"ts": 1751610729, "freq": 7.83, "amp": -2.83}, {"ts": 1751613689, "freq": 7.83, "amp": -2.29}, {"ts": 1751617721, "freq": 7.83, "amp": -1.83}, {"ts": 1751621007, "freq": 7.83, "amp": -0.36}, {"ts": 1751624552, "freq": 7.83, "amp": -2.12}, {"ts": 1751627920, "freq": 7.83, "amp": -2.22}]